fnspace/__init__.py
fnspace/core.py
fnspace-0.3.2.dist-info/METADATA
fnspace-0.3.2.dist-info/WHEEL
fnspace-0.3.2.dist-info/top_level.txt
fnspace-0.3.2.dist-info/RECORD
